llama_index/llms/watsonx/__init__.py
llama_index/llms/watsonx/base.py
llama_index/llms/watsonx/utils.py
llama_index_llms_watsonx-0.1.8.dist-info/METADATA
llama_index_llms_watsonx-0.1.8.dist-info/WHEEL
llama_index_llms_watsonx-0.1.8.dist-info/RECORD
