Metadata-Version: 2.1
Name: llama-index-llms-watsonx
Version: 0.1.8
Summary: llama-index llms watsonx integration
License: MIT
Author: Your Name
Author-email: you@example.com
Requires-Python: >=3.10,<4.0
Classifier: License :: OSI Approved :: MIT License
Classifier: Programming Language :: Python :: 3
Classifier: Programming Language :: Python :: 3.10
Classifier: Programming Language :: Python :: 3.11
Classifier: Programming Language :: Python :: 3.12
Requires-Dist: ibm-watson-machine-learning (>=1.0.342,<2.0.0)
Requires-Dist: llama-index-core (>=0.10.11.post1,<0.11.0)
